pger/__init__.py
pger/__main__.py
pger/const.py
pger/pypi.py
pger/templates/MANIFEST.in
pger/templates/README.md
pger/templates/conftest.py
pger/templates/pyproject.toml
pger/templates/python-publish.yml
pger/templates/requirements.txt
pger/templates/started-notify.yml
pger/templates/update-version.py
pger-0.0.12.dist-info/LICENSE
pger-0.0.12.dist-info/METADATA
pger-0.0.12.dist-info/WHEEL
pger-0.0.12.dist-info/entry_points.txt
pger-0.0.12.dist-info/top_level.txt
pger-0.0.12.dist-info/RECORD
