Metadata-Version: 2.1
Name: pger
Version: 0.0.12
Summary: python package generator
Author-email: foyou <yimi.0822@qq.com>
Project-URL: Source, https://github.com/foyoux/pger
Project-URL: Homepage, https://github.com/foyoux/pger
Project-URL: Bug Tracker, https://github.com/foyoux/pger/issues
Keywords: python,package,pypi,setuptools,generator
Classifier: Programming Language :: Python
Classifier: Programming Language :: Python :: 3
Classifier: Programming Language :: Python :: 3.7
Classifier: Programming Language :: Python :: 3.8
Classifier: Programming Language :: Python :: 3.9
Classifier: Programming Language :: Python :: 3.10
Classifier: Programming Language :: Python :: 3.11
Classifier: License :: OSI Approved :: MIT License
Classifier: Environment :: Console
Requires-Python: >=3.7
License-File: LICENSE
